vbjax/__init__.py
vbjax/_version.py
vbjax/connectome.py
vbjax/coupling.py
vbjax/diagnostics.py
vbjax/embed.py
vbjax/layers.py
vbjax/loops.py
vbjax/monitor.py
vbjax/neural_mass.py
vbjax/regmap.py
vbjax/shtlc.py
vbjax/sparse.py
vbjax/util.py
vbjax/app/dopa/__init__.py
vbjax/app/dopa/sweep.py
vbjax/app/dopa/tavg_bold.py
vbjax/app/vep/__init__.py
vbjax/tests/__init__.py
vbjax/tests/__main__.py
vbjax/tests/bench_vmap.py
vbjax/tests/test_connectome.py
vbjax/tests/test_coupling.py
vbjax/tests/test_embed.py
vbjax/tests/test_field_inference.py
vbjax/tests/test_jaxisms.py
vbjax/tests/test_layers.py
vbjax/tests/test_loops.py
vbjax/tests/test_models.py
vbjax/tests/test_monitor.py
vbjax/tests/test_regmap.py
vbjax/tests/test_shtlc.py
vbjax/tests/test_sparse.py
vbjax/tests/test_uloop.py
vbjax-0.0.16.dist-info/METADATA
vbjax-0.0.16.dist-info/WHEEL
vbjax-0.0.16.dist-info/licenses/LICENSE
vbjax-0.0.16.dist-info/RECORD
