Metadata-Version: 2.3
Name: vbjax
Version: 0.0.16
Summary: Virtual brains w/ JAX
Project-URL: Homepage, https://github.com/ins-amu/vbjax
Project-URL: Bug Tracker, https://github.com/ins-amu/vbjax/issues
Author-email: Marmaduke Woodman <marmaduke.woodman@univ-amu.fr>
Classifier: Development Status :: 4 - Beta
Classifier: License :: OSI Approved :: Apache Software License
Classifier: Operating System :: OS Independent
Classifier: Programming Language :: Python :: 3
Classifier: Topic :: Scientific/Engineering :: Artificial Intelligence
Requires-Dist: jax
Requires-Dist: jax-dataclasses
Requires-Dist: jaxlib
Requires-Dist: numpy
Requires-Dist: numpyro
Requires-Dist: scipy
Provides-Extra: dev
Requires-Dist: build; extra == 'dev'
Requires-Dist: grip; extra == 'dev'
Requires-Dist: jedi-language-server; extra == 'dev'
Requires-Dist: joblib; extra == 'dev'
Requires-Dist: jupyter; extra == 'dev'
Requires-Dist: matplotlib; extra == 'dev'
Requires-Dist: pytest; extra == 'dev'
Requires-Dist: pytest-benchmark; extra == 'dev'
Requires-Dist: pytest-xdist; extra == 'dev'
Requires-Dist: python-lsp-server[all]; extra == 'dev'
Requires-Dist: tqdm; extra == 'dev'
Requires-Dist: twine; extra == 'dev'
